LICENCE
README.md
setup.py
mathfunctions_eckhardt/__init__.py
mathfunctions_eckhardt/mathfunctions.py
mathfunctions_eckhardt.egg-info/PKG-INFO
mathfunctions_eckhardt.egg-info/SOURCES.txt
mathfunctions_eckhardt.egg-info/dependency_links.txt
mathfunctions_eckhardt.egg-info/top_level.txt